client.py
create.py
delete.py
info.py
list.py
marvlcli.py
ssh.py
mypkg/client.py
mypkg/create.py
mypkg/delete.py
mypkg/info.py
mypkg/list.py
mypkg/marvlcli.py
mypkg/ssh.py
package_data/myuserdata_marv_default.txt
package_data/payloads.yaml
marvlcli-0.0.27.dist-info/METADATA
marvlcli-0.0.27.dist-info/WHEEL
marvlcli-0.0.27.dist-info/entry_points.txt
marvlcli-0.0.27.dist-info/top_level.txt
marvlcli-0.0.27.dist-info/RECORD
